Workbook

Sheet 使い方
B2: 越境EC事業 財務モデル
B3: 作成: 2026年8月 / 単位: 特記なき場合は日本円
B6: ■ 使い方
B7: ① 「前提」シート | C7: 青字のセルを自分の商材の数字に書き換えます。ここだけ触れば全シートが連動します。
B8: ② 「単位経済性」シート | C8: 1商品を1個売ったときの損益。実質貢献利益率が12%未満なら、その商材は成立しません。
B9: ③ 「月次PL」シート | C9: 24ヶ月の売上・貢献利益・固定費。青字の月商と貢献利益率を実績に置き換えて使います。
B10: ④ 「感度分析」シート | C10: 仕入原価率と広告費率を動かしたときの実質貢献利益率。赤い領域に入る商材は扱いません。
B11: ⑤ 「販売台帳」シート | C11: 出荷1件ごとの記録テンプレート。消費税還付の証憑管理を兼ねます。
B13: ■ 色のルール
B14: 青字 | C14: 手で入力する値。ここを書き換えてください。
B15: 黒字 | C15: 数式で計算される値。書き換えないでください。
B16: 緑字 | C16: 他のシートを参照している値。書き換えないでください。
B17: 黄色の塗り | C17: 特に重要な前提。事業の成否を左右します。
B19: ■ 注意
B20: 数値はすべて仮置きです | C20: 自社の実績が出たら、必ず実測値に置き換えてください。推定値のまま意思決定をしないこと。
B21: 税務判断ではありません | C21: 消費税還付・輸出免税の適用可否は、必ず税理士に確認してください。
B22: 制度変更に注意 | C22: 米国のde minimis廃止・EUの関税改正により、関税前提は変動します。四半期ごとに見直してください。

Sheet 前提
A1: 前提条件
A2: 青字のセルを書き換えてください。黄色は事業の成否を左右する重要前提です。
A4: 【基本】
A5: 為替レート (JPY/USD) | B5: 150 | C5: 計画時のレート。四半期ごとに見直す
A6: 消費税率 | B6: 0.1 | C6: 輸出免税により仕入分が還付される
A8: 【単位経済性の前提（1商品あたり）】
A9: 販売価格 (USD) | B9: 120 | C9: $80未満は成立しにくい（de minimis廃止後）
A10: 仕入原価・税抜 (JPY) | B10: 6000 | C10: 最重要変数。仕入先開拓で下げる
A11: 販売手数料率（モール） | B11: 0.15 | C11: Amazon 15% / eBay 13〜15%
A12: 出荷手数料 (USD/件) | B12: 6.5 | C12: FBA手数料。直送なら0にして送料へ寄せる
A13: 広告費率（TACoS） | B13: 0.12 | C13: 立ち上げ期は15〜20%。改善余地が大きい
A14: 国際送料・通関費の按分 (USD/件) | B14: 9 | C14: まとめ輸入で下がる
A15: 関税率（実効・売価比） | B15: 0.1 | C15: 2026年のde minimis廃止で新規発生。HSコード次第
A16: 決済・為替コスト率 | B16: 0.015 | C16: 外貨受取手段で変わる
A17: 返品・損失率 | B17: 0.04 | C17: カテゴリにより2〜8%
A19: 【月次固定費 (JPY)】
A20: 役員報酬 | B20: 300000
A21: 倉庫・保管 | B21: 50000 | C21: 自宅併用なら按分
A22: 税理士顧問料 | B22: 30000 | C22: 越境EC実績のある事務所を選ぶ
A23: ツール・通信 | B23: 20000
A24: 保険・雑費 | B24: 25000 | C24: 海外PL保険を含む
A25: 月次固定費 合計 | B25: =SUM(B20:B24) -> 425000
A27: 【初期費用 (JPY)】
A28: 合同会社 設立費用 | B28: 60000 | C28: 電子定款。司法書士報酬込みなら10万円程度
A29: 古物商許可 申請 | B29: 20000 | C29: 中古を扱うなら必須。約40日かかる
A30: 印鑑・登記事項証明書等 | B30: 20000
A31: 初期仕入れ | B31: 2000000 | C31: 20〜30SKU分。1SKUあたり上限5〜10万円で分散
A32: 撮影機材・梱包資材・PC | B32: 300000
A33: 保険（年払） | B33: 50000
A34: 会計ソフト・ツール初期 | B34: 50000
A35: 運転資金バッファ | B35: 1500000 | C35: 固定費3ヶ月分＋追加仕入れ
A36: 初期費用 合計 | B36: =SUM(B28:B35) -> 4000000
A38: 【資金】
A39: 創業時 自己資金 (JPY) | B39: 4000000 | C39: 推奨レンジ 300〜500万円
A40: 初期費用差引後の残高 | B40: =B39-B36 -> 0 | C40: マイナスなら自己資金か初期費用の見直しが必要
A42: 【運転資金の前提】
A43: 在庫日数（仕入→販売） | B43: 60 | C43: 目標は60日以下
A44: 売掛日数（販売→入金） | B44: 14 | C44: Amazonは約2週間サイクル
A45: 買掛日数（仕入→支払） | B45: 0 | C45: 現金仕入れなら0
A46: 現金循環日数 (CCC) | B46: =B43+B44-B45 -> 74 | C46: 90日以下が目標。成長期は運転資金が先に必要になる

Sheet 単位経済性
A1: 単位経済性（1商品を1個売ったときの損益）
A2: 緑字は「前提」シートを参照しています。数字を変えたい場合は「前提」シートを編集してください。
A4: 項目 | B4: USD | C4: JPY | D4: 売価比 | E4: 備考
A5: 売上 | B5: =前提!$B$9 -> 120 | C5: =B5*前提!$B$5 -> 18000 | D5: =B5/$B$5 -> 1 | E5: 2026年のde minimis廃止により$80未満は成立しにくい
A6: 仕入原価（税抜） | B6: =-前提!$B$10/前提!$B$5 -> -40 | C6: =B6*前提!$B$5 -> -6000 | D6: =B6/$B$5 -> -0.33333333 | E6: 最重要変数。ここを下げるのが唯一最大の競争優位
A7: 販売手数料 | B7: =-$B$5*前提!$B$11 -> -18 | C7: =B7*前提!$B$5 -> -2700 | D7: =B7/$B$5 -> -0.15 | E7: Amazon 15% / eBay 13〜15%
A8: 出荷手数料 | B8: =-前提!$B$12 -> -6.5 | C8: =B8*前提!$B$5 -> -975 | D8: =B8/$B$5 -> -0.054166667 | E8: FBA手数料
A9: 広告費 | B9: =-$B$5*前提!$B$13 -> -14.4 | C9: =B9*前提!$B$5 -> -2160 | D9: =B9/$B$5 -> -0.12 | E9: TACoS。改善余地が最も大きい
A10: 国際送料・通関費 | B10: =-前提!$B$14 -> -9 | C10: =B10*前提!$B$5 -> -1350 | D10: =B10/$B$5 -> -0.075 | E10: まとめ輸入で下がる
A11: 関税（DDP） | B11: =-$B$5*前提!$B$15 -> -12 | C11: =B11*前提!$B$5 -> -1800 | D11: =B11/$B$5 -> -0.1 | E11: 2026年に新規発生した原価。制御できない
A12: 決済・為替コスト | B12: =-$B$5*前提!$B$16 -> -1.8 | C12: =B12*前提!$B$5 -> -270 | D12: =B12/$B$5 -> -0.015 | E12: 外貨受取手段で変わる
A13: 返品・損失引当 | B13: =-$B$5*前提!$B$17 -> -4.8 | C13: =B13*前提!$B$5 -> -720 | D13: =B13/$B$5 -> -0.04 | E13: カテゴリにより2〜8%
A14: 貢献利益（税還付前） | B14: =SUM(B5:B13) -> 13.5 | C14: =B14*前提!$B$5 -> 2025 | D14: =B14/$B$5 -> 0.1125 | E14: この時点でマイナスなら即撤退
A15: 消費税還付（仕入税額の戻り） | B15: =前提!$B$10*前提!$B$6/前提!$B$5 -> 4 | C15: =B15*前提!$B$5 -> 600 | D15: =B15/$B$5 -> 0.033333333 | E15: 輸出免税による。証憑保存を怠るとこれが消える
A16: 実質貢献利益 | B16: =B14+B15 -> 17.5 | C16: =B16*前提!$B$5 -> 2625 | D16: =B16/$B$5 -> 0.14583333 | E16: ★これが事業の実力値
A18: 【判定】
A19: 実質貢献利益率 | B19: =B16/$B$5 -> 0.14583333 | C19: =IF(B19>=0.18,"◎ 目標水準（18%以上）",IF(B19>=0.12,"○ 成立ライン（12%以上）","✕ 成立しない（12%未満）")) -> ○ 成立ライン（12%以上）
A20: 仕入原価率 | B20: =-B6/$B$5 -> 0.33333333 | C20: =IF(B20<=0.33,"◎ 良好",IF(B20<=0.38,"○ 許容範囲","✕ 高すぎる")) -> ○ 許容範囲
A21: 実質貢献利益額 (USD/件) | B21: =B16 -> 17.5 | C21: =IF(B21>=25,"◎ 良好",IF(B21>=12,"○ 工数を回収できる","✕ 1件あたりの手間に見合わない")) -> ○ 工数を回収できる
A23: 【損益分岐】
A24: 月次固定費 (JPY) | B24: =前提!$B$25 -> 425000
A25: 損益分岐 月商 (JPY) | B25: =IF(B19<=0,"—",B24/B19) -> 2914285.7
A26: 必要 月間出荷件数 | B26: =IF(OR(B19<=0,C5=0),"—",B25/C5) -> 161.90476 | E26: 1件あたり工数25〜38分。月160件で約70〜100時間
A27: 必要 1日あたり出荷件数 | B27: =IF(B26="—","—",B26/22) -> 7.3593074 | E27: 月22営業日で計算
A29: 【運転資金の目安】
A30: 想定月商 (JPY) | B30: 5500000 | E30: この月商のときに在庫と売掛に沈む金額を試算する
A31: 必要運転資金 (JPY) | B31: =B30*(前提!$B$46/30)*B20 -> 4522222.2 | E31: 月商 × (CCC÷30) × 仕入原価率。成長するほど現金が足りなくなる

Sheet 月次PL
A1: 24ヶ月 損益計画
A2: 青字（月商・実質貢献利益率・固定費）を実績や自分の計画に置き換えてください。
A4: 月 | B4: 月商 (JPY) | C4: 実質貢献利益率 | D4: 貢献利益 (JPY) | E4: 固定費 (JPY) | F4: 営業損益 (JPY) | G4: 累計営業損益 (JPY) | H4: 出荷件数 | I4: 備考
A5: M1 | B5: 0 | C5: 0 | D5: =B5*C5 -> 0 | E5: 425000 | F5: =D5-E5 -> -425000 | G5: =F5 -> -425000 | H5: =IF(単位経済性!$C$5=0,0,B5/単位経済性!$C$5) -> 0 | I5: 設立・許認可・仕入準備
A6: M2 | B6: 300000 | C6: 0.08 | D6: =B6*C6 -> 24000 | E6: 425000 | F6: =D6-E6 -> -401000 | G6: =G5+F6 -> -826000 | H6: =IF(単位経済性!$C$5=0,0,B6/単位経済性!$C$5) -> 16.666667 | I6: 初出荷
A7: M3 | B7: 600000 | C7: 0.1 | D7: =B7*C7 -> 60000 | E7: 425000 | F7: =D7-E7 -> -365000 | G7: =G6+F7 -> -1191000 | H7: =IF(単位経済性!$C$5=0,0,B7/単位経済性!$C$5) -> 33.333333
A8: M4 | B8: 1000000 | C8: 0.12 | D8: =B8*C8 -> 120000 | E8: 425000 | F8: =D8-E8 -> -305000 | G8: =G7+F8 -> -1496000 | H8: =IF(単位経済性!$C$5=0,0,B8/単位経済性!$C$5) -> 55.555556
A9: M5 | B9: 1400000 | C9: 0.13 | D9: =B9*C9 -> 182000 | E9: 425000 | F9: =D9-E9 -> -243000 | G9: =G8+F9 -> -1739000 | H9: =IF(単位経済性!$C$5=0,0,B9/単位経済性!$C$5) -> 77.777778
A10: M6 | B10: 1800000 | C10: 0.14 | D10: =B10*C10 -> 252000 | E10: 425000 | F10: =D10-E10 -> -173000 | G10: =G9+F10 -> -1912000 | H10: =IF(単位経済性!$C$5=0,0,B10/単位経済性!$C$5) -> 100 | I10: Phase 1 開始
A11: M7 | B11: 2300000 | C11: 0.15 | D11: =B11*C11 -> 345000 | E11: 425000 | F11: =D11-E11 -> -80000 | G11: =G10+F11 -> -1992000 | H11: =IF(単位経済性!$C$5=0,0,B11/単位経済性!$C$5) -> 127.77778
A12: M8 | B12: 2800000 | C12: 0.16 | D12: =B12*C12 -> 448000 | E12: 450000 | F12: =D12-E12 -> -2000 | G12: =G11+F12 -> -1994000 | H12: =IF(単位経済性!$C$5=0,0,B12/単位経済性!$C$5) -> 155.55556 | I12: ★ 損益分岐点
A13: M9 | B13: 3300000 | C13: 0.16 | D13: =B13*C13 -> 528000 | E13: 450000 | F13: =D13-E13 -> 78000 | G13: =G12+F13 -> -1916000 | H13: =IF(単位経済性!$C$5=0,0,B13/単位経済性!$C$5) -> 183.33333
A14: M10 | B14: 4000000 | C14: 0.17 | D14: =B14*C14 -> 680000 | E14: 550000 | F14: =D14-E14 -> 130000 | G14: =G13+F14 -> -1786000 | H14: =IF(単位経済性!$C$5=0,0,B14/単位経済性!$C$5) -> 222.22222
A15: M11 | B15: 4700000 | C15: 0.17 | D15: =B15*C15 -> 799000 | E15: 550000 | F15: =D15-E15 -> 249000 | G15: =G14+F15 -> -1537000 | H15: =IF(単位経済性!$C$5=0,0,B15/単位経済性!$C$5) -> 261.11111
A16: M12 | B16: 5500000 | C16: 0.18 | D16: =B16*C16 -> 990000 | E16: 550000 | F16: =D16-E16 -> 440000 | G16: =G15+F16 -> -1097000 | H16: =IF(単位経済性!$C$5=0,0,B16/単位経済性!$C$5) -> 305.55556 | I16: Phase 2 判断 / 融資検討
A17: M13 | B17: 6000000 | C17: 0.18 | D17: =B17*C17 -> 1080000 | E17: 700000 | F17: =D17-E17 -> 380000 | G17: =G16+F17 -> -717000 | H17: =IF(単位経済性!$C$5=0,0,B17/単位経済性!$C$5) -> 333.33333 | I17: 2年目開始
A18: M14 | B18: 7000000 | C18: 0.19 | D18: =B18*C18 -> 1330000 | E18: 700000 | F18: =D18-E18 -> 630000 | G18: =G17+F18 -> -87000 | H18: =IF(単位経済性!$C$5=0,0,B18/単位経済性!$C$5) -> 388.88889
A19: M15 | B19: 8000000 | C19: 0.19 | D19: =B19*C19 -> 1520000 | E19: 700000 | F19: =D19-E19 -> 820000 | G19: =G18+F19 -> 733000 | H19: =IF(単位経済性!$C$5=0,0,B19/単位経済性!$C$5) -> 444.44444
A20: M16 | B20: 9000000 | C20: 0.2 | D20: =B20*C20 -> 1800000 | E20: 900000 | F20: =D20-E20 -> 900000 | G20: =G19+F20 -> 1633000 | H20: =IF(単位経済性!$C$5=0,0,B20/単位経済性!$C$5) -> 500
A21: M17 | B21: 9500000 | C21: 0.2 | D21: =B21*C21 -> 1900000 | E21: 900000 | F21: =D21-E21 -> 1000000 | G21: =G20+F21 -> 2633000 | H21: =IF(単位経済性!$C$5=0,0,B21/単位経済性!$C$5) -> 527.77778
A22: M18 | B22: 10000000 | C22: 0.2 | D22: =B22*C22 -> 2000000 | E22: 900000 | F22: =D22-E22 -> 1100000 | G22: =G21+F22 -> 3733000 | H22: =IF(単位経済性!$C$5=0,0,B22/単位経済性!$C$5) -> 555.55556
A23: M19 | B23: 10500000 | C23: 0.2 | D23: =B23*C23 -> 2100000 | E23: 1000000 | F23: =D23-E23 -> 1100000 | G23: =G22+F23 -> 4833000 | H23: =IF(単位経済性!$C$5=0,0,B23/単位経済性!$C$5) -> 583.33333
A24: M20 | B24: 10500000 | C24: 0.21 | D24: =B24*C24 -> 2205000 | E24: 1000000 | F24: =D24-E24 -> 1205000 | G24: =G23+F24 -> 6038000 | H24: =IF(単位経済性!$C$5=0,0,B24/単位経済性!$C$5) -> 583.33333
A25: M21 | B25: 11000000 | C25: 0.21 | D25: =B25*C25 -> 2310000 | E25: 1000000 | F25: =D25-E25 -> 1310000 | G25: =G24+F25 -> 7348000 | H25: =IF(単位経済性!$C$5=0,0,B25/単位経済性!$C$5) -> 611.11111
A26: M22 | B26: 11500000 | C26: 0.21 | D26: =B26*C26 -> 2415000 | E26: 1100000 | F26: =D26-E26 -> 1315000 | G26: =G25+F26 -> 8663000 | H26: =IF(単位経済性!$C$5=0,0,B26/単位経済性!$C$5) -> 638.88889
A27: M23 | B27: 12000000 | C27: 0.21 | D27: =B27*C27 -> 2520000 | E27: 1100000 | F27: =D27-E27 -> 1420000 | G27: =G26+F27 -> 10083000 | H27: =IF(単位経済性!$C$5=0,0,B27/単位経済性!$C$5) -> 666.66667
A28: M24 | B28: 12500000 | C28: 0.22 | D28: =B28*C28 -> 2750000 | E28: 1100000 | F28: =D28-E28 -> 1650000 | G28: =G27+F28 -> 11733000 | H28: =IF(単位経済性!$C$5=0,0,B28/単位経済性!$C$5) -> 694.44444 | I28: —
A30: Y1 合計 | B30: =SUM(B5:B16) -> 27700000 | C30: =IF(B30=0,0,D30/B30) -> 0.1598556 | D30: =SUM(D5:D16) -> 4428000 | E30: =SUM(E5:E16) -> 5525000 | F30: =SUM(F5:F16) -> -1097000 | H30: =SUM(H5:H16) -> 1538.8889
A31: Y2 合計 | B31: =SUM(B17:B28) -> 117500000 | C31: =IF(B31=0,0,D31/B31) -> 0.20365957 | D31: =SUM(D17:D28) -> 23930000 | E31: =SUM(E17:E28) -> 11100000 | F31: =SUM(F17:F28) -> 12830000 | H31: =SUM(H17:H28) -> 6527.7778
A33: 【健全性チェック】
A34: Y1 営業損益 | B34: =F30 -> -1097000 | D34: =IF(B34>=0,"黒字","赤字（1年目の赤字は正常）") -> 赤字（1年目の赤字は正常）
A35: 自己資金で吸収できるか | B35: =前提!$B$40+F30 -> -1097000 | D35: =IF(B35>=0,"○ Y1を自己資金で乗り切れる","✕ 追加資金が必要。創業融資を検討") -> ✕ 追加資金が必要。創業融資を検討
A36: 黒字転換月 | B36: =IFERROR(INDEX($A$5:$A$28,MATCH(TRUE(),INDEX($F$5:$F$28>=0,0),0)),"—") -> M9

Sheet 感度分析
A1: 感度分析：実質貢献利益率
A2: 行＝仕入原価率、列＝広告費率。その他の前提は「前提」シートに従います。
A3: 12%未満（赤）の領域に入る商材は扱わない。18%以上（緑）が目標水準。
A5: 仕入原価率 ＼ 広告費率 | B5: 0.05 | C5: 0.075 | D5: 0.1 | E5: 0.125 | F5: 0.15 | G5: 0.175 | H5: 0.2
A6: 0.25 | B6: =1-$A6-B$5-前提!$B$11-前提!$B$12/前提!$B$9-前提!$B$14/前提!$B$9-前提!$B$15-前提!$B$16-前提!$B$17+$A6*前提!$B$6 -> 0.29083333 | C6: =1-$A6-C$5-前提!$B$11-前提!$B$12/前提!$B$9-前提!$B$14/前提!$B$9-前提!$B$15-前提!$B$16-前提!$B$17+$A6*前提!$B$6 -> 0.26583333 | D6: =1-$A6-D$5-前提!$B$11-前提!$B$12/前提!$B$9-前提!$B$14/前提!$B$9-前提!$B$15-前提!$B$16-前提!$B$17+$A6*前提!$B$6 -> 0.24083333 | E6: =1-$A6-E$5-前提!$B$11-前提!$B$12/前提!$B$9-前提!$B$14/前提!$B$9-前提!$B$15-前提!$B$16-前提!$B$17+$A6*前提!$B$6 -> 0.21583333 | F6: =1-$A6-F$5-前提!$B$11-前提!$B$12/前提!$B$9-前提!$B$14/前提!$B$9-前提!$B$15-前提!$B$16-前提!$B$17+$A6*前提!$B$6 -> 0.19083333 | G6: =1-$A6-G$5-前提!$B$11-前提!$B$12/前提!$B$9-前提!$B$14/前提!$B$9-前提!$B$15-前提!$B$16-前提!$B$17+$A6*前提!$B$6 -> 0.16583333 | H6: =1-$A6-H$5-前提!$B$11-前提!$B$12/前提!$B$9-前提!$B$14/前提!$B$9-前提!$B$15-前提!$B$16-前提!$B$17+$A6*前提!$B$6 -> 0.14083333 | L6: 計算式：実質貢献利益率 ＝ 1 − 仕入原価率 − 広告費率 − 販売手数料率
A7: 0.275 | B7: =1-$A7-B$5-前提!$B$11-前提!$B$12/前提!$B$9-前提!$B$14/前提!$B$9-前提!$B$15-前提!$B$16-前提!$B$17+$A7*前提!$B$6 -> 0.26833333 | C7: =1-$A7-C$5-前提!$B$11-前提!$B$12/前提!$B$9-前提!$B$14/前提!$B$9-前提!$B$15-前提!$B$16-前提!$B$17+$A7*前提!$B$6 -> 0.24333333 | D7: =1-$A7-D$5-前提!$B$11-前提!$B$12/前提!$B$9-前提!$B$14/前提!$B$9-前提!$B$15-前提!$B$16-前提!$B$17+$A7*前提!$B$6 -> 0.21833333 | E7: =1-$A7-E$5-前提!$B$11-前提!$B$12/前提!$B$9-前提!$B$14/前提!$B$9-前提!$B$15-前提!$B$16-前提!$B$17+$A7*前提!$B$6 -> 0.19333333 | F7: =1-$A7-F$5-前提!$B$11-前提!$B$12/前提!$B$9-前提!$B$14/前提!$B$9-前提!$B$15-前提!$B$16-前提!$B$17+$A7*前提!$B$6 -> 0.16833333 | G7: =1-$A7-G$5-前提!$B$11-前提!$B$12/前提!$B$9-前提!$B$14/前提!$B$9-前提!$B$15-前提!$B$16-前提!$B$17+$A7*前提!$B$6 -> 0.14333333 | H7: =1-$A7-H$5-前提!$B$11-前提!$B$12/前提!$B$9-前提!$B$14/前提!$B$9-前提!$B$15-前提!$B$16-前提!$B$17+$A7*前提!$B$6 -> 0.11833333 | L7: − 出荷手数料/売価 − 送料/売価 − 関税率 − 決済率 − 返品率
A8: 0.3 | B8: =1-$A8-B$5-前提!$B$11-前提!$B$12/前提!$B$9-前提!$B$14/前提!$B$9-前提!$B$15-前提!$B$16-前提!$B$17+$A8*前提!$B$6 -> 0.24583333 | C8: =1-$A8-C$5-前提!$B$11-前提!$B$12/前提!$B$9-前提!$B$14/前提!$B$9-前提!$B$15-前提!$B$16-前提!$B$17+$A8*前提!$B$6 -> 0.22083333 | D8: =1-$A8-D$5-前提!$B$11-前提!$B$12/前提!$B$9-前提!$B$14/前提!$B$9-前提!$B$15-前提!$B$16-前提!$B$17+$A8*前提!$B$6 -> 0.19583333 | E8: =1-$A8-E$5-前提!$B$11-前提!$B$12/前提!$B$9-前提!$B$14/前提!$B$9-前提!$B$15-前提!$B$16-前提!$B$17+$A8*前提!$B$6 -> 0.17083333 | F8: =1-$A8-F$5-前提!$B$11-前提!$B$12/前提!$B$9-前提!$B$14/前提!$B$9-前提!$B$15-前提!$B$16-前提!$B$17+$A8*前提!$B$6 -> 0.14583333 | G8: =1-$A8-G$5-前提!$B$11-前提!$B$12/前提!$B$9-前提!$B$14/前提!$B$9-前提!$B$15-前提!$B$16-前提!$B$17+$A8*前提!$B$6 -> 0.12083333 | H8: =1-$A8-H$5-前提!$B$11-前提!$B$12/前提!$B$9-前提!$B$14/前提!$B$9-前提!$B$15-前提!$B$16-前提!$B$17+$A8*前提!$B$6 -> 0.095833333 | L8: ＋ 仕入原価率 × 消費税率（＝輸出免税による還付）
A9: 0.325 | B9: =1-$A9-B$5-前提!$B$11-前提!$B$12/前提!$B$9-前提!$B$14/前提!$B$9-前提!$B$15-前提!$B$16-前提!$B$17+$A9*前提!$B$6 -> 0.22333333 | C9: =1-$A9-C$5-前提!$B$11-前提!$B$12/前提!$B$9-前提!$B$14/前提!$B$9-前提!$B$15-前提!$B$16-前提!$B$17+$A9*前提!$B$6 -> 0.19833333 | D9: =1-$A9-D$5-前提!$B$11-前提!$B$12/前提!$B$9-前提!$B$14/前提!$B$9-前提!$B$15-前提!$B$16-前提!$B$17+$A9*前提!$B$6 -> 0.17333333 | E9: =1-$A9-E$5-前提!$B$11-前提!$B$12/前提!$B$9-前提!$B$14/前提!$B$9-前提!$B$15-前提!$B$16-前提!$B$17+$A9*前提!$B$6 -> 0.14833333 | F9: =1-$A9-F$5-前提!$B$11-前提!$B$12/前提!$B$9-前提!$B$14/前提!$B$9-前提!$B$15-前提!$B$16-前提!$B$17+$A9*前提!$B$6 -> 0.12333333 | G9: =1-$A9-G$5-前提!$B$11-前提!$B$12/前提!$B$9-前提!$B$14/前提!$B$9-前提!$B$15-前提!$B$16-前提!$B$17+$A9*前提!$B$6 -> 0.098333333 | H9: =1-$A9-H$5-前提!$B$11-前提!$B$12/前提!$B$9-前提!$B$14/前提!$B$9-前提!$B$15-前提!$B$16-前提!$B$17+$A9*前提!$B$6 -> 0.073333333
A10: 0.35 | B10: =1-$A10-B$5-前提!$B$11-前提!$B$12/前提!$B$9-前提!$B$14/前提!$B$9-前提!$B$15-前提!$B$16-前提!$B$17+$A10*前提!$B$6 -> 0.20083333 | C10: =1-$A10-C$5-前提!$B$11-前提!$B$12/前提!$B$9-前提!$B$14/前提!$B$9-前提!$B$15-前提!$B$16-前提!$B$17+$A10*前提!$B$6 -> 0.17583333 | D10: =1-$A10-D$5-前提!$B$11-前提!$B$12/前提!$B$9-前提!$B$14/前提!$B$9-前提!$B$15-前提!$B$16-前提!$B$17+$A10*前提!$B$6 -> 0.15083333 | E10: =1-$A10-E$5-前提!$B$11-前提!$B$12/前提!$B$9-前提!$B$14/前提!$B$9-前提!$B$15-前提!$B$16-前提!$B$17+$A10*前提!$B$6 -> 0.12583333 | F10: =1-$A10-F$5-前提!$B$11-前提!$B$12/前提!$B$9-前提!$B$14/前提!$B$9-前提!$B$15-前提!$B$16-前提!$B$17+$A10*前提!$B$6 -> 0.10083333 | G10: =1-$A10-G$5-前提!$B$11-前提!$B$12/前提!$B$9-前提!$B$14/前提!$B$9-前提!$B$15-前提!$B$16-前提!$B$17+$A10*前提!$B$6 -> 0.075833333 | H10: =1-$A10-H$5-前提!$B$11-前提!$B$12/前提!$B$9-前提!$B$14/前提!$B$9-前提!$B$15-前提!$B$16-前提!$B$17+$A10*前提!$B$6 -> 0.050833333 | L10: 現状の前提（原価率33.3% / 広告12%）は表の中央付近にあります。
A11: 0.375 | B11: =1-$A11-B$5-前提!$B$11-前提!$B$12/前提!$B$9-前提!$B$14/前提!$B$9-前提!$B$15-前提!$B$16-前提!$B$17+$A11*前提!$B$6 -> 0.17833333 | C11: =1-$A11-C$5-前提!$B$11-前提!$B$12/前提!$B$9-前提!$B$14/前提!$B$9-前提!$B$15-前提!$B$16-前提!$B$17+$A11*前提!$B$6 -> 0.15333333 | D11: =1-$A11-D$5-前提!$B$11-前提!$B$12/前提!$B$9-前提!$B$14/前提!$B$9-前提!$B$15-前提!$B$16-前提!$B$17+$A11*前提!$B$6 -> 0.12833333 | E11: =1-$A11-E$5-前提!$B$11-前提!$B$12/前提!$B$9-前提!$B$14/前提!$B$9-前提!$B$15-前提!$B$16-前提!$B$17+$A11*前提!$B$6 -> 0.10333333 | F11: =1-$A11-F$5-前提!$B$11-前提!$B$12/前提!$B$9-前提!$B$14/前提!$B$9-前提!$B$15-前提!$B$16-前提!$B$17+$A11*前提!$B$6 -> 0.078333333 | G11: =1-$A11-G$5-前提!$B$11-前提!$B$12/前提!$B$9-前提!$B$14/前提!$B$9-前提!$B$15-前提!$B$16-前提!$B$17+$A11*前提!$B$6 -> 0.053333333 | H11: =1-$A11-H$5-前提!$B$11-前提!$B$12/前提!$B$9-前提!$B$14/前提!$B$9-前提!$B$15-前提!$B$16-前提!$B$17+$A11*前提!$B$6 -> 0.028333333 | L11: 赤い領域に落ちる商材は、いくら売っても利益が残りません。
A12: 0.4 | B12: =1-$A12-B$5-前提!$B$11-前提!$B$12/前提!$B$9-前提!$B$14/前提!$B$9-前提!$B$15-前提!$B$16-前提!$B$17+$A12*前提!$B$6 -> 0.15583333 | C12: =1-$A12-C$5-前提!$B$11-前提!$B$12/前提!$B$9-前提!$B$14/前提!$B$9-前提!$B$15-前提!$B$16-前提!$B$17+$A12*前提!$B$6 -> 0.13083333 | D12: =1-$A12-D$5-前提!$B$11-前提!$B$12/前提!$B$9-前提!$B$14/前提!$B$9-前提!$B$15-前提!$B$16-前提!$B$17+$A12*前提!$B$6 -> 0.10583333 | E12: =1-$A12-E$5-前提!$B$11-前提!$B$12/前提!$B$9-前提!$B$14/前提!$B$9-前提!$B$15-前提!$B$16-前提!$B$17+$A12*前提!$B$6 -> 0.080833333 | F12: =1-$A12-F$5-前提!$B$11-前提!$B$12/前提!$B$9-前提!$B$14/前提!$B$9-前提!$B$15-前提!$B$16-前提!$B$17+$A12*前提!$B$6 -> 0.055833333 | G12: =1-$A12-G$5-前提!$B$11-前提!$B$12/前提!$B$9-前提!$B$14/前提!$B$9-前提!$B$15-前提!$B$16-前提!$B$17+$A12*前提!$B$6 -> 0.030833333 | H12: =1-$A12-H$5-前提!$B$11-前提!$B$12/前提!$B$9-前提!$B$14/前提!$B$9-前提!$B$15-前提!$B$16-前提!$B$17+$A12*前提!$B$6 -> 0.0058333333
A13: 0.425 | B13: =1-$A13-B$5-前提!$B$11-前提!$B$12/前提!$B$9-前提!$B$14/前提!$B$9-前提!$B$15-前提!$B$16-前提!$B$17+$A13*前提!$B$6 -> 0.13333333 | C13: =1-$A13-C$5-前提!$B$11-前提!$B$12/前提!$B$9-前提!$B$14/前提!$B$9-前提!$B$15-前提!$B$16-前提!$B$17+$A13*前提!$B$6 -> 0.10833333 | D13: =1-$A13-D$5-前提!$B$11-前提!$B$12/前提!$B$9-前提!$B$14/前提!$B$9-前提!$B$15-前提!$B$16-前提!$B$17+$A13*前提!$B$6 -> 0.083333333 | E13: =1-$A13-E$5-前提!$B$11-前提!$B$12/前提!$B$9-前提!$B$14/前提!$B$9-前提!$B$15-前提!$B$16-前提!$B$17+$A13*前提!$B$6 -> 0.058333333 | F13: =1-$A13-F$5-前提!$B$11-前提!$B$12/前提!$B$9-前提!$B$14/前提!$B$9-前提!$B$15-前提!$B$16-前提!$B$17+$A13*前提!$B$6 -> 0.033333333 | G13: =1-$A13-G$5-前提!$B$11-前提!$B$12/前提!$B$9-前提!$B$14/前提!$B$9-前提!$B$15-前提!$B$16-前提!$B$17+$A13*前提!$B$6 -> 0.0083333333 | H13: =1-$A13-H$5-前提!$B$11-前提!$B$12/前提!$B$9-前提!$B$14/前提!$B$9-前提!$B$15-前提!$B$16-前提!$B$17+$A13*前提!$B$6 -> -0.016666667
A14: 0.45 | B14: =1-$A14-B$5-前提!$B$11-前提!$B$12/前提!$B$9-前提!$B$14/前提!$B$9-前提!$B$15-前提!$B$16-前提!$B$17+$A14*前提!$B$6 -> 0.11083333 | C14: =1-$A14-C$5-前提!$B$11-前提!$B$12/前提!$B$9-前提!$B$14/前提!$B$9-前提!$B$15-前提!$B$16-前提!$B$17+$A14*前提!$B$6 -> 0.085833333 | D14: =1-$A14-D$5-前提!$B$11-前提!$B$12/前提!$B$9-前提!$B$14/前提!$B$9-前提!$B$15-前提!$B$16-前提!$B$17+$A14*前提!$B$6 -> 0.060833333 | E14: =1-$A14-E$5-前提!$B$11-前提!$B$12/前提!$B$9-前提!$B$14/前提!$B$9-前提!$B$15-前提!$B$16-前提!$B$17+$A14*前提!$B$6 -> 0.035833333 | F14: =1-$A14-F$5-前提!$B$11-前提!$B$12/前提!$B$9-前提!$B$14/前提!$B$9-前提!$B$15-前提!$B$16-前提!$B$17+$A14*前提!$B$6 -> 0.010833333 | G14: =1-$A14-G$5-前提!$B$11-前提!$B$12/前提!$B$9-前提!$B$14/前提!$B$9-前提!$B$15-前提!$B$16-前提!$B$17+$A14*前提!$B$6 -> -0.014166667 | H14: =1-$A14-H$5-前提!$B$11-前提!$B$12/前提!$B$9-前提!$B$14/前提!$B$9-前提!$B$15-前提!$B$16-前提!$B$17+$A14*前提!$B$6 -> -0.039166667
A17: 【為替感応度】
A18: 為替 (JPY/USD) | B18: 130 | C18: 135 | D18: 140 | E18: 145 | F18: 150 | G18: 155 | H18: 160 | I18: 165
A19: 仕入原価率 | B19: =前提!$B$10/B$18/前提!$B$9 -> 0.38461538 | C19: =前提!$B$10/C$18/前提!$B$9 -> 0.37037037 | D19: =前提!$B$10/D$18/前提!$B$9 -> 0.35714286 | E19: =前提!$B$10/E$18/前提!$B$9 -> 0.34482759 | F19: =前提!$B$10/F$18/前提!$B$9 -> 0.33333333 | G19: =前提!$B$10/G$18/前提!$B$9 -> 0.32258065 | H19: =前提!$B$10/H$18/前提!$B$9 -> 0.3125 | I19: =前提!$B$10/I$18/前提!$B$9 -> 0.3030303
A20: 実質貢献利益率 | B20: =1-B19-前提!$B$13-前提!$B$11-前提!$B$12/前提!$B$9-前提!$B$14/前提!$B$9-前提!$B$15-前提!$B$16-前提!$B$17+B19*前提!$B$6 -> 0.099679487 | C20: =1-C19-前提!$B$13-前提!$B$11-前提!$B$12/前提!$B$9-前提!$B$14/前提!$B$9-前提!$B$15-前提!$B$16-前提!$B$17+C19*前提!$B$6 -> 0.1125 | D20: =1-D19-前提!$B$13-前提!$B$11-前提!$B$12/前提!$B$9-前提!$B$14/前提!$B$9-前提!$B$15-前提!$B$16-前提!$B$17+D19*前提!$B$6 -> 0.12440476 | E20: =1-E19-前提!$B$13-前提!$B$11-前提!$B$12/前提!$B$9-前提!$B$14/前提!$B$9-前提!$B$15-前提!$B$16-前提!$B$17+E19*前提!$B$6 -> 0.13548851 | F20: =1-F19-前提!$B$13-前提!$B$11-前提!$B$12/前提!$B$9-前提!$B$14/前提!$B$9-前提!$B$15-前提!$B$16-前提!$B$17+F19*前提!$B$6 -> 0.14583333 | G20: =1-G19-前提!$B$13-前提!$B$11-前提!$B$12/前提!$B$9-前提!$B$14/前提!$B$9-前提!$B$15-前提!$B$16-前提!$B$17+G19*前提!$B$6 -> 0.15551075 | H20: =1-H19-前提!$B$13-前提!$B$11-前提!$B$12/前提!$B$9-前提!$B$14/前提!$B$9-前提!$B$15-前提!$B$16-前提!$B$17+H19*前提!$B$6 -> 0.16458333 | I20: =1-I19-前提!$B$13-前提!$B$11-前提!$B$12/前提!$B$9-前提!$B$14/前提!$B$9-前提!$B$15-前提!$B$16-前提!$B$17+I19*前提!$B$6 -> 0.17310606
A22: 円高（左）に振れると利益が消えます。円高でも12%を割らない原価率の商材を選ぶことが唯一の防御です。

Sheet 販売台帳
A1: 販売台帳（出荷1件ごとに記録）
A2: この台帳が消費税還付の根拠になります。「輸出証憑リンク」の列を絶対に空にしないでください。
A3: 下の行は記入例です。実際に使うときは書き換えるか削除してください。
A5: 注文ID | B5: 販売日 | C5: チャネル | D5: SKU | E5: 品名 | F5: 売価(USD) | G5: 為替 | H5: 売上(JPY) | I5: 仕入原価(JPY) | J5: 販売手数料(JPY) | K5: 広告費(JPY) | L5: 送料(JPY) | M5: 関税(JPY) | N5: 返品有無 | O5: 仕向国 | P5: 発送方法 | Q5: 発送日 | R5: 伝票番号 | S5: 輸出証憑リンク | T5: 消費税還付相当(JPY) | U5: 実質貢献利益(JPY) | V5: 貢献利益率
A6: ORD-2026-0001 | B6: 2026-10-05 | C6: eBay | D6: CAM-0012 | E6: Nikon F3 Body (Used, Excellent) | F6: 320 | G6: 150 | H6: =F6*G6 -> 48000 | I6: 20000 | J6: =H6*前提!$B$11 -> 7200 | K6: 2400 | L6: 3200 | M6: =H6*前提!$B$15 -> 4800 | N6: 無 | O6: USA | P6: DHL Express | Q6: 2026-10-06 | R6: 1234567890 | S6: drive.google.com/...ORD-2026-0001 | T6: =I6*前提!$B$6 -> 2000 | U6: =H6-I6-J6-K6-L6-M6+T6 -> 12400 | V6: =IF(H6=0,0,U6/H6) -> 0.25833333
H7: =IF(F7="","",F7*G7) | J7: =IF(H7="","",H7*前提!$B$11) | M7: =IF(H7="","",H7*前提!$B$15) | T7: =IF(I7="","",I7*前提!$B$6) | U7: =IF(H7="","",H7-N(I7)-N(J7)-N(K7)-N(L7)-N(M7)+N(T7)) | V7: =IF(OR(H7="",H7=0),"",U7/H7)
H8: =IF(F8="","",F8*G8) | J8: =IF(H8="","",H8*前提!$B$11) | M8: =IF(H8="","",H8*前提!$B$15) | T8: =IF(I8="","",I8*前提!$B$6) | U8: =IF(H8="","",H8-N(I8)-N(J8)-N(K8)-N(L8)-N(M8)+N(T8)) | V8: =IF(OR(H8="",H8=0),"",U8/H8)
H9: =IF(F9="","",F9*G9) | J9: =IF(H9="","",H9*前提!$B$11) | M9: =IF(H9="","",H9*前提!$B$15) | T9: =IF(I9="","",I9*前提!$B$6) | U9: =IF(H9="","",H9-N(I9)-N(J9)-N(K9)-N(L9)-N(M9)+N(T9)) | V9: =IF(OR(H9="",H9=0),"",U9/H9)
H10: =IF(F10="","",F10*G10) | J10: =IF(H10="","",H10*前提!$B$11) | M10: =IF(H10="","",H10*前提!$B$15) | T10: =IF(I10="","",I10*前提!$B$6) | U10: =IF(H10="","",H10-N(I10)-N(J10)-N(K10)-N(L10)-N(M10)+N(T10)) | V10: =IF(OR(H10="",H10=0),"",U10/H10)
H11: =IF(F11="","",F11*G11) | J11: =IF(H11="","",H11*前提!$B$11) | M11: =IF(H11="","",H11*前提!$B$15) | T11: =IF(I11="","",I11*前提!$B$6) | U11: =IF(H11="","",H11-N(I11)-N(J11)-N(K11)-N(L11)-N(M11)+N(T11)) | V11: =IF(OR(H11="",H11=0),"",U11/H11)
H12: =IF(F12="","",F12*G12) | J12: =IF(H12="","",H12*前提!$B$11) | M12: =IF(H12="","",H12*前提!$B$15) | T12: =IF(I12="","",I12*前提!$B$6) | U12: =IF(H12="","",H12-N(I12)-N(J12)-N(K12)-N(L12)-N(M12)+N(T12)) | V12: =IF(OR(H12="",H12=0),"",U12/H12)
H13: =IF(F13="","",F13*G13) | J13: =IF(H13="","",H13*前提!$B$11) | M13: =IF(H13="","",H13*前提!$B$15) | T13: =IF(I13="","",I13*前提!$B$6) | U13: =IF(H13="","",H13-N(I13)-N(J13)-N(K13)-N(L13)-N(M13)+N(T13)) | V13: =IF(OR(H13="",H13=0),"",U13/H13)
H14: =IF(F14="","",F14*G14) | J14: =IF(H14="","",H14*前提!$B$11) | M14: =IF(H14="","",H14*前提!$B$15) | T14: =IF(I14="","",I14*前提!$B$6) | U14: =IF(H14="","",H14-N(I14)-N(J14)-N(K14)-N(L14)-N(M14)+N(T14)) | V14: =IF(OR(H14="",H14=0),"",U14/H14)
H15: =IF(F15="","",F15*G15) | J15: =IF(H15="","",H15*前提!$B$11) | M15: =IF(H15="","",H15*前提!$B$15) | T15: =IF(I15="","",I15*前提!$B$6) | U15: =IF(H15="","",H15-N(I15)-N(J15)-N(K15)-N(L15)-N(M15)+N(T15)) | V15: =IF(OR(H15="",H15=0),"",U15/H15)
H16: =IF(F16="","",F16*G16) | J16: =IF(H16="","",H16*前提!$B$11) | M16: =IF(H16="","",H16*前提!$B$15) | T16: =IF(I16="","",I16*前提!$B$6) | U16: =IF(H16="","",H16-N(I16)-N(J16)-N(K16)-N(L16)-N(M16)+N(T16)) | V16: =IF(OR(H16="",H16=0),"",U16/H16)
H17: =IF(F17="","",F17*G17) | J17: =IF(H17="","",H17*前提!$B$11) | M17: =IF(H17="","",H17*前提!$B$15) | T17: =IF(I17="","",I17*前提!$B$6) | U17: =IF(H17="","",H17-N(I17)-N(J17)-N(K17)-N(L17)-N(M17)+N(T17)) | V17: =IF(OR(H17="",H17=0),"",U17/H17)
H18: =IF(F18="","",F18*G18) | J18: =IF(H18="","",H18*前提!$B$11) | M18: =IF(H18="","",H18*前提!$B$15) | T18: =IF(I18="","",I18*前提!$B$6) | U18: =IF(H18="","",H18-N(I18)-N(J18)-N(K18)-N(L18)-N(M18)+N(T18)) | V18: =IF(OR(H18="",H18=0),"",U18/H18)
... H26: =IF(F26="","",F26*G26) | J26: =IF(H26="","",H26*前提!$B$11) | M26: =IF(H26="","",H26*前提!$B$15) | T26: =IF(I26="","",I26*前提!$B$6) | U26: =IF(H26="","",H26-N(I26)-N(J26)-N(K26)-N(L26)-N(M26)+N(T26)) | V26: =IF(OR(H26="",H26=0),"",U26/H26)
